monobank-api/__init__.py
monobank-api/client.py
monobank-api/errors.py
monobank-api/helpers.py
monobank-api/signature.py
monobank-api/transport.py
monobank_api/__init__.py
monobank_api/client.py
monobank_api/errors.py
monobank_api/helpers.py
monobank_api/signature.py
monobank_api/transport.py
monobank_api-0.1.2.data/scripts/monobank
monobank_api-0.1.2.data/scripts/monobank-api
monobank_api-0.1.2.data/scripts/monobank_api
monobank_api-0.1.2.dist-info/LICENSE
monobank_api-0.1.2.dist-info/METADATA
monobank_api-0.1.2.dist-info/WHEEL
monobank_api-0.1.2.dist-info/top_level.txt
monobank_api-0.1.2.dist-info/RECORD
