Metadata-Version: 2.1
Name: monobank-api
Version: 0.1.2
Summary: The Monobank API wrapper for Python
Home-page: https://github.com/edicasoft/monobank-api
Author: Serhii Zahranychnyi
Author-email: serhii.z@edicasoft.com
License: UNKNOWN
Platform: UNKNOWN
Classifier: Programming Language :: Python :: 3
Classifier: License :: OSI Approved :: MIT License
Classifier: Operating System :: OS Independent
Requires-Python: >=3.6
Requires-Dist: ecdsa (==0.14.1)
Requires-Dist: requests (==2.22.0)
